airflow/providers/microsoft/azure/__init__.py
airflow/providers/microsoft/azure/example_dags/__init__.py
airflow/providers/microsoft/azure/example_dags/example_adls_delete.py
airflow/providers/microsoft/azure/example_dags/example_azure_blob_to_gcs.py
airflow/providers/microsoft/azure/example_dags/example_azure_container_instances.py
airflow/providers/microsoft/azure/example_dags/example_azure_cosmosdb.py
airflow/providers/microsoft/azure/example_dags/example_file_to_wasb.py
airflow/providers/microsoft/azure/example_dags/example_fileshare.py
airflow/providers/microsoft/azure/example_dags/example_local_to_adls.py
airflow/providers/microsoft/azure/hooks/__init__.py
airflow/providers/microsoft/azure/hooks/adx.py
airflow/providers/microsoft/azure/hooks/azure_batch.py
airflow/providers/microsoft/azure/hooks/azure_container_instance.py
airflow/providers/microsoft/azure/hooks/azure_container_registry.py
airflow/providers/microsoft/azure/hooks/azure_container_volume.py
airflow/providers/microsoft/azure/hooks/azure_cosmos.py
airflow/providers/microsoft/azure/hooks/azure_data_factory.py
airflow/providers/microsoft/azure/hooks/azure_data_lake.py
airflow/providers/microsoft/azure/hooks/azure_fileshare.py
airflow/providers/microsoft/azure/hooks/base_azure.py
airflow/providers/microsoft/azure/hooks/wasb.py
airflow/providers/microsoft/azure/log/__init__.py
airflow/providers/microsoft/azure/log/wasb_task_handler.py
airflow/providers/microsoft/azure/operators/__init__.py
airflow/providers/microsoft/azure/operators/adls_delete.py
airflow/providers/microsoft/azure/operators/adls_list.py
airflow/providers/microsoft/azure/operators/adx.py
airflow/providers/microsoft/azure/operators/azure_batch.py
airflow/providers/microsoft/azure/operators/azure_container_instances.py
airflow/providers/microsoft/azure/operators/azure_cosmos.py
airflow/providers/microsoft/azure/operators/wasb_delete_blob.py
airflow/providers/microsoft/azure/secrets/__init__.py
apache_airflow_backport_providers_microsoft_azure-2021.3.13.dist-info/LICENSE
apache_airflow_backport_providers_microsoft_azure-2021.3.13.dist-info/METADATA
apache_airflow_backport_providers_microsoft_azure-2021.3.13.dist-info/NOTICE
apache_airflow_backport_providers_microsoft_azure-2021.3.13.dist-info/WHEEL
apache_airflow_backport_providers_microsoft_azure-2021.3.13.dist-info/top_level.txt
apache_airflow_backport_providers_microsoft_azure-2021.3.13.dist-info/RECORD
