Metadata-Version: 2.1
Name: apache-airflow-backport-providers-microsoft-azure
Version: 2021.3.13
Summary: Backport provider package apache-airflow-backport-providers-microsoft-azure for Apache Airflow
Home-page: https://airflow.apache.org/
Author: Apache Software Foundation
Author-email: dev@airflow.apache.org
License: Apache License 2.0
Download-URL: https://archive.apache.org/dist/airflow/backport-providers
Project-URL: Documentation, https://airflow.apache.org/docs/
Project-URL: Bug Tracker, https://github.com/apache/airflow/issues
Project-URL: Source Code, https://github.com/apache/airflow
Platform: UNKNOWN
Classifier: Development Status :: 5 - Production/Stable
Classifier: Environment :: Console
Classifier: Environment :: Web Environment
Classifier: Intended Audience :: Developers
Classifier: Intended Audience :: System Administrators
Classifier: License :: OSI Approved :: Apache Software License
Classifier: Programming Language :: Python :: 3.6
Classifier: Programming Language :: Python :: 3.7
Classifier: Programming Language :: Python :: 3.8
Classifier: Topic :: System :: Monitoring
Requires-Python: ~=3.6
Requires-Dist: apache-airflow (~=1.10)
Requires-Dist: azure-batch (>=8.0.0)
Requires-Dist: azure-cosmos (<4,>=3.0.1)
Requires-Dist: azure-datalake-store (>=0.0.45)
Requires-Dist: azure-identity (>=1.3.1)
Requires-Dist: azure-keyvault (>=4.1.0)
Requires-Dist: azure-kusto-data (<0.1,>=0.0.43)
Requires-Dist: azure-mgmt-containerinstance (<2.0,>=1.5.0)
Requires-Dist: azure-mgmt-datafactory (<2.0,>=1.0.0)
Requires-Dist: azure-mgmt-datalake-store (>=0.5.0)
Requires-Dist: azure-mgmt-resource (>=2.2.0)
Requires-Dist: azure-storage-blob (>=12.7.0)
Requires-Dist: azure-storage-common (>=2.1.0)
Requires-Dist: azure-storage-file (>=2.1.0)
Provides-Extra: google
Requires-Dist: apache-airflow-backport-providers-google ; extra == 'google'
Provides-Extra: oracle
Requires-Dist: apache-airflow-backport-providers-oracle ; extra == 'oracle'
